audfactory/__init__.py
audfactory/core/__init__.py
audfactory/core/api.py
audfactory/core/lookup.py
docs/changelog.rst
docs/conf.py
docs/contributing.rst
docs/genindex.rst
docs/index.rst
docs/installation.rst
docs/requirements.txt
docs/usage.rst
docs/_templates/autosummary/base.rst
docs/_templates/autosummary/class.rst
docs/_templates/autosummary/function.rst
docs/api-src/audfactory.rst
tests/conftest.py
tests/requirements.txt
tests/test_api.py
tests/test_lookup.py
audfactory-1.0.15.dist-info/LICENSE
audfactory-1.0.15.dist-info/METADATA
audfactory-1.0.15.dist-info/WHEEL
audfactory-1.0.15.dist-info/top_level.txt
audfactory-1.0.15.dist-info/RECORD
