Metadata-Version: 2.1
Name: audfactory
Version: 1.0.15
Summary: Communicate with Artifactory
Author-email: Hagen Wierstorf <hwierstorf@audeering.com>, Johannes Wagner <jwagner@audeering.com>
License: MIT License
Project-URL: repository, https://github.com/audeering/audfactory/
Project-URL: documentation, https://audeering.github.io/audfactory/
Keywords: artifactory
Classifier: Development Status :: 5 - Production/Stable
Classifier: Intended Audience :: Science/Research
Classifier: Intended Audience :: Developers
Classifier: License :: OSI Approved :: MIT License
Classifier: Operating System :: OS Independent
Classifier: Programming Language :: Python
Classifier: Programming Language :: Python :: 3
Classifier: Programming Language :: Python :: 3.8
Classifier: Programming Language :: Python :: 3.9
Classifier: Programming Language :: Python :: 3.10
Classifier: Programming Language :: Python :: 3.11
Classifier: Topic :: Scientific/Engineering
License-File: LICENSE
Requires-Dist: audeer >=1.11.0
Requires-Dist: dohq-artifactory >=0.9.1
